hermano/__init__.py
hermano/cli.py
hermano/commands/__init__.py
hermano/commands/epub_commands.py
hermano-0.1.2.dist-info/METADATA
hermano-0.1.2.dist-info/WHEEL
hermano-0.1.2.dist-info/entry_points.txt
hermano-0.1.2.dist-info/top_level.txt
hermano-0.1.2.dist-info/RECORD
