Metadata-Version: 2.2
Name: hermano
Version: 0.1.2
Summary: LLM-powered CLI tool for daily tasks
Home-page: https://github.com/hermano-tools/hermano-cli
Author: Manohar
Author-email: example@example.com
Classifier: Development Status :: 3 - Alpha
Classifier: Intended Audience :: Developers
Classifier: License :: OSI Approved :: MIT License
Classifier: Programming Language :: Python :: 3
Classifier: Programming Language :: Python :: 3.8
Classifier: Programming Language :: Python :: 3.9
Classifier: Programming Language :: Python :: 3.10
Requires-Python: >=3.8
Requires-Dist: click>=8.1.0
Requires-Dist: ebooklib>=0.17.1
Requires-Dist: beautifulsoup4>=4.10.0
Requires-Dist: openai>=1.0.0
Requires-Dist: tiktoken>=0.5.0
Requires-Dist: python-dotenv>=1.0.0
Requires-Dist: requests>=2.28.0
Requires-Dist: rich>=13.0.0
Dynamic: author
Dynamic: author-email
Dynamic: classifier
Dynamic: description
Dynamic: description-content-type
Dynamic: home-page
Dynamic: requires-dist
Dynamic: requires-python
Dynamic: summary
